rbt_mcp_server/.python-version
rbt_mcp_server/README.md
rbt_mcp_server/__init__.py
rbt_mcp_server/errors.py
rbt_mcp_server/graphiti_tools.py
rbt_mcp_server/models.py
rbt_mcp_server/path_resolver.py
rbt_mcp_server/server.py
rbt_mcp_server/.claude/settings.local.json
rbt_mcp_server/chunking/__init__.py
rbt_mcp_server/chunking/add_document.py
rbt_mcp_server/chunking/comparator.py
rbt_mcp_server/chunking/graphiti_client.py
rbt_mcp_server/chunking/markdown_chunker.py
rbt_mcp_server/chunking/models.py
rbt_mcp_server/chunking/rbt_chunker.py
rbt_mcp_server/converter/__init__.py
rbt_mcp_server/converter/builder.py
rbt_mcp_server/converter/converter.py
rbt_mcp_server/converter/generator.py
rbt_mcp_server/converter/parser.py
rbt_mcp_server-0.3.2.dist-info/METADATA
rbt_mcp_server-0.3.2.dist-info/WHEEL
rbt_mcp_server-0.3.2.dist-info/entry_points.txt
rbt_mcp_server-0.3.2.dist-info/RECORD
