Metadata-Version: 2.4
Name: rbt-mcp-server
Version: 0.3.2
Summary: MCP Server for Graphiti memory and document chunking with intelligent Markdown processing.
Project-URL: Homepage, https://github.com/yourusername/KnowledgeSmith
Project-URL: Repository, https://github.com/yourusername/KnowledgeSmith
Project-URL: Issues, https://github.com/yourusername/KnowledgeSmith/issues
Author-email: Devin Lai <leo7nel23@gmail.com>
License: MIT
Keywords: document-editor,llm,mcp,rbt,token-optimization
Classifier: Development Status :: 4 - Beta
Classifier: Intended Audience :: Developers
Classifier: License :: OSI Approved :: MIT License
Classifier: Programming Language :: Python :: 3
Classifier: Programming Language :: Python :: 3.10
Classifier: Programming Language :: Python :: 3.11
Classifier: Programming Language :: Python :: 3.12
Requires-Python: >=3.10
Requires-Dist: graphiti-core>=0.3.0
Requires-Dist: jsonschema>=4.0.0
Requires-Dist: mcp>=1.0.0
Requires-Dist: pyyaml>=6.0.0
Requires-Dist: referencing>=0.30.0
Requires-Dist: rpds-py>=0.20.0
Provides-Extra: dev
Requires-Dist: pytest-cov>=4.0.0; extra == 'dev'
Requires-Dist: pytest>=7.0.0; extra == 'dev'
